mathiago/Sequencias_elementares.py
mathiago/__init__.py
mathiago/teoria_dos_numeros.py
mathiago-0.0.1.dist-info/METADATA
mathiago-0.0.1.dist-info/WHEEL
mathiago-0.0.1.dist-info/top_level.txt
mathiago-0.0.1.dist-info/RECORD
