Metadata-Version: 2.1
Name: mathiago
Version: 0.0.1
Summary: Pacote com funções matemáticas para treino em python
Home-page: https://github.com/Tavarestiag
Author: tavares_tiag
Author-email: tiagoalvestavares1@gmail.com
Requires-Python: >=3.8
